{
  "_fv": 24,
  "_type": "tool",
  "definition": {
    "renderType": 0,
    "texture": "knife",
    "customModelName": "Normal",
    "name": "Knife",
    "specialInfo": [],
    "creativeTab": {
      "value": "TOOLS"
    },
    "toolType": "Sword",
    "harvestLevel": 0,
    "efficiency": 4.0,
    "attackSpeed": 7.0,
    "enchantability": 13,
    "damageVsEntity": 0.7,
    "usageCount": 500,
    "blocksAffected": [],
    "hasGlow": false,
    "repairItems": [],
    "immuneToFire": false,
    "stayInGridWhenCrafting": false,
    "damageOnCrafting": false,
    "onEntityHitWith": {
      "name": "KnifeLivingEntityIsHitWithTool"
    }
  }
}